pycodebuddy/__init__.py
pycodebuddy/base_client.py
pycodebuddy/codebuddy.py
pycodebuddy/command_executor.py
pycodebuddy/config_loader.py
pycodebuddy/dummy_client.py
pycodebuddy/file_handler.py
pycodebuddy/main.py
pycodebuddy/openai_client.py
pycodebuddy/transaction_handler.py
pycodebuddy-0.0.1.dist-info/METADATA
pycodebuddy-0.0.1.dist-info/WHEEL
pycodebuddy-0.0.1.dist-info/entry_points.txt
pycodebuddy-0.0.1.dist-info/RECORD
