Metadata-Version: 2.1
Name: pycodebuddy
Version: 0.0.1
Summary: A command-line tool leveraging OpenAI's GPT for intelligent project management within a Git-integrated shell.
License: MIT
Keywords: GPT,automation,OpenAI,interactive shell,Git,project management
Author: Cem Basoglu
Author-email: cem.basoglu@web.de
Requires-Python: >=3.9
Classifier: Development Status :: 4 - Beta
Classifier: Intended Audience :: Developers
Classifier: License :: OSI Approved :: MIT License
Classifier: Programming Language :: Python :: 3
Classifier: Programming Language :: Python :: 3.9
Classifier: Programming Language :: Python :: 3.10
Classifier: Programming Language :: Python :: 3.11
Classifier: Programming Language :: Python :: 3.12
Classifier: Programming Language :: Python :: 3.13
Classifier: Programming Language :: Python :: 3.8
Requires-Dist: gitignore-parser (>=0.1.11,<0.2.0)
Requires-Dist: openai (>=1.54.4)
Requires-Dist: pyyaml (>=6.0.2)
